{"userStory":{"id":159,"what":"I want to find a link on the sponsorships page to become a 350 level sponsor","who":"AuthenticatedUser","why":"so that I can pay for and become a sponsor role."},"questions":[{"question":{"id":3,"descricao":"Does the user story implementation involve any sensitive transactions, data, or API?"},"done":true,"questoesEspecificas":[{"question":{"id":8,"descricao":"Does the user story implementation involve using any sensitive data or API ?","fk_Questao_Geral_id":3},"done":true,"requirements":[{"descricao":"Verify that all sensitive data created and processed by the application has been identified, and ensure that a policy is in place on how to deal with sensitive data. ([C8](https://owasp.org/www-project-proactive-controls/#div-numbering))","id":85,"id_externo":"V8.3.4","fk_Secao_id":48,"fk_Questao_Especifica_id":8,"nivel":"L1","marked":true}]}]}],"finished":"2025-04-24T14:41:55.581Z","started":"2025-04-24T14:41:47.857Z"}